{
  "wcid": 1960,
  "weenieType": 1,
  "boolStats": [
    {
      "key": 1,
      "value": 1
    },
    {
      "key": 11,
      "value": 1
    },
    {
      "key": 18,
      "value": 1
    }
  ],
  "intStats": [
    {
      "key": 81,
      "value": 2
    },
    {
      "key": 82,
      "value": 1
    },
    {
      "key": 93,
      "value": 1044
    }
  ],
  "didStats": [
    {
      "key": 1,
      "value": 33555051
    },
    {
      "key": 8,
      "value": 100667494
    }
  ],
  "iidStats": [],
  "floatStats": [
    {
      "key": 41,
      "value": 600.0
    },
    {
      "key": 43,
      "value": 15.0
    }
  ],
  "int64Stats": [],
  "stringStats": [
    {
      "key": 1,
      "value": "Extreme Direlands Forest Generator"
    }
  ],
  "generatorTable": [
    {
      "delay": 1800.0,
      "frame": {
        "origin": {
          "x": 0.0,
          "y": 0.0,
          "z": 0.0
        },
        "angles": {
          "w": 1.0,
          "x": 0.0,
          "y": 0.0,
          "z": 0.0
        }
      },
      "initCreate": 1,
      "maxNum": 2,
      "objcell_id": 0,
      "probability": 0.014999999664723873,
      "ptid": 0,
      "shade": 0.0,
      "slot": 0,
      "stackSize": -1,
      "type": 8057,
      "whenCreate": 1,
      "whereCreate": 2
    },
    {
      "delay": 1800.0,
      "frame": {
        "origin": {
          "x": 0.0,
          "y": 0.0,
          "z": 0.0
        },
        "angles": {
          "w": 1.0,
          "x": 0.0,
          "y": 0.0,
          "z": 0.0
        }
      },
      "initCreate": 1,
      "maxNum": 2,
      "objcell_id": 0,
      "probability": 0.034540001302957535,
      "ptid": 0,
      "shade": 0.0,
      "slot": 1,
      "stackSize": -1,
      "type": 7982,
      "whenCreate": 1,
      "whereCreate": 2
    },
    {
      "delay": 1800.0,
      "frame": {
        "origin": {
          "x": 0.0,
          "y": 0.0,
          "z": 0.0
        },
        "angles": {
          "w": 1.0,
          "x": 0.0,
          "y": 0.0,
          "z": 0.0
        }
      },
      "initCreate": 1,
      "maxNum": 2,
      "objcell_id": 0,
      "probability": 0.05407999828457832,
      "ptid": 0,
      "shade": 0.0,
      "slot": 2,
      "stackSize": -1,
      "type": 8056,
      "whenCreate": 1,
      "whereCreate": 2
    },
    {
      "delay": 1800.0,
      "frame": {
        "origin": {
          "x": 0.0,
          "y": 0.0,
          "z": 0.0
        },
        "angles": {
          "w": 1.0,
          "x": 0.0,
          "y": 0.0,
          "z": 0.0
        }
      },
      "initCreate": 1,
      "maxNum": 2,
      "objcell_id": 0,
      "probability": 0.07361999899148941,
      "ptid": 0,
      "shade": 0.0,
      "slot": 3,
      "stackSize": -1,
      "type": 7983,
      "whenCreate": 1,
      "whereCreate": 2
    },
    {
      "delay": 1800.0,
      "frame": {
        "origin": {
          "x": 0.0,
          "y": 0.0,
          "z": 0.0
        },
        "angles": {
          "w": 1.0,
          "x": 0.0,
          "y": 0.0,
          "z": 0.0
        }
      },
      "initCreate": 1,
      "maxNum": 2,
      "objcell_id": 0,
      "probability": 0.0931600034236908,
      "ptid": 0,
      "shade": 0.0,
      "slot": 4,
      "stackSize": -1,
      "type": 15267,
      "whenCreate": 1,
      "whereCreate": 2
    },
    {
      "delay": 1800.0,
      "frame": {
        "origin": {
          "x": 0.0,
          "y": 0.0,
          "z": 0.0
        },
        "angles": {
          "w": 1.0,
          "x": 0.0,
          "y": 0.0,
          "z": 0.0
        }
      },
      "initCreate": 1,
      "maxNum": 2,
      "objcell_id": 0,
      "probability": 0.09404200315475464,
      "ptid": 0,
      "shade": 0.0,
      "slot": 5,
      "stackSize": -1,
      "type": 14801,
      "whenCreate": 1,
      "whereCreate": 2
    },
    {
      "delay": 1800.0,
      "frame": {
        "origin": {
          "x": 0.0,
          "y": 0.0,
          "z": 0.0
        },
        "angles": {
          "w": 1.0,
          "x": 0.0,
          "y": 0.0,
          "z": 0.0
        }
      },
      "initCreate": 1,
      "maxNum": 2,
      "objcell_id": 0,
      "probability": 0.11358200013637543,
      "ptid": 0,
      "shade": 0.0,
      "slot": 6,
      "stackSize": -1,
      "type": 7097,
      "whenCreate": 1,
      "whereCreate": 2
    },
    {
      "delay": 1800.0,
      "frame": {
        "origin": {
          "x": 0.0,
          "y": 0.0,
          "z": 0.0
        },
        "angles": {
          "w": 1.0,
          "x": 0.0,
          "y": 0.0,
          "z": 0.0
        }
      },
      "initCreate": 1,
      "maxNum": 2,
      "objcell_id": 0,
      "probability": 0.1419599950313568,
      "ptid": 0,
      "shade": 0.0,
      "slot": 7,
      "stackSize": -1,
      "type": 22206,
      "whenCreate": 1,
      "whereCreate": 2
    },
    {
      "delay": 1800.0,
      "frame": {
        "origin": {
          "x": 0.0,
          "y": 0.0,
          "z": 0.0
        },
        "angles": {
          "w": 1.0,
          "x": 0.0,
          "y": 0.0,
          "z": 0.0
        }
      },
      "initCreate": 1,
      "maxNum": 2,
      "objcell_id": 0,
      "probability": 0.14677000045776367,
      "ptid": 0,
      "shade": 0.0,
      "slot": 8,
      "stackSize": -1,
      "type": 27564,
      "whenCreate": 1,
      "whereCreate": 2
    },
    {
      "delay": 1800.0,
      "frame": {
        "origin": {
          "x": 0.0,
          "y": 0.0,
          "z": 0.0
        },
        "angles": {
          "w": 1.0,
          "x": 0.0,
          "y": 0.0,
          "z": 0.0
        }
      },
      "initCreate": 1,
      "maxNum": 2,
      "objcell_id": 0,
      "probability": 0.16630999743938446,
      "ptid": 0,
      "shade": 0.0,
      "slot": 9,
      "stackSize": -1,
      "type": 14520,
      "whenCreate": 1,
      "whereCreate": 2
    },
    {
      "delay": 1800.0,
      "frame": {
        "origin": {
          "x": 0.0,
          "y": 0.0,
          "z": 0.0
        },
        "angles": {
          "w": 1.0,
          "x": 0.0,
          "y": 0.0,
          "z": 0.0
        }
      },
      "initCreate": 1,
      "maxNum": 2,
      "objcell_id": 0,
      "probability": 0.17112000286579132,
      "ptid": 0,
      "shade": 0.0,
      "slot": 10,
      "stackSize": -1,
      "type": 19543,
      "whenCreate": 1,
      "whereCreate": 2
    },
    {
      "delay": 1800.0,
      "frame": {
        "origin": {
          "x": 0.0,
          "y": 0.0,
          "z": 0.0
        },
        "angles": {
          "w": 1.0,
          "x": 0.0,
          "y": 0.0,
          "z": 0.0
        }
      },
      "initCreate": 1,
      "maxNum": 2,
      "objcell_id": 0,
      "probability": 0.1906599998474121,
      "ptid": 0,
      "shade": 0.0,
      "slot": 11,
      "stackSize": -1,
      "type": 22054,
      "whenCreate": 1,
      "whereCreate": 2
    },
    {
      "delay": 1800.0,
      "frame": {
        "origin": {
          "x": 0.0,
          "y": 0.0,
          "z": 0.0
        },
        "angles": {
          "w": 1.0,
          "x": 0.0,
          "y": 0.0,
          "z": 0.0
        }
      },
      "initCreate": 1,
      "maxNum": 2,
      "objcell_id": 0,
      "probability": 0.2101999968290329,
      "ptid": 0,
      "shade": 0.0,
      "slot": 12,
      "stackSize": -1,
      "type": 22914,
      "whenCreate": 1,
      "whereCreate": 2
    },
    {
      "delay": 1800.0,
      "frame": {
        "origin": {
          "x": 0.0,
          "y": 0.0,
          "z": 0.0
        },
        "angles": {
          "w": 1.0,
          "x": 0.0,
          "y": 0.0,
          "z": 0.0
        }
      },
      "initCreate": 1,
      "maxNum": 2,
      "objcell_id": 0,
      "probability": 0.2297399938106537,
      "ptid": 0,
      "shade": 0.0,
      "slot": 13,
      "stackSize": -1,
      "type": 23489,
      "whenCreate": 1,
      "whereCreate": 2
    },
    {
      "delay": 1800.0,
      "frame": {
        "origin": {
          "x": 0.0,
          "y": 0.0,
          "z": 0.0
        },
        "angles": {
          "w": 1.0,
          "x": 0.0,
          "y": 0.0,
          "z": 0.0
        }
      },
      "initCreate": 1,
      "maxNum": 2,
      "objcell_id": 0,
      "probability": 0.24928000569343567,
      "ptid": 0,
      "shade": 0.0,
      "slot": 14,
      "stackSize": -1,
      "type": 22053,
      "whenCreate": 1,
      "whereCreate": 2
    },
    {
      "delay": 1800.0,
      "frame": {
        "origin": {
          "x": 0.0,
          "y": 0.0,
          "z": 0.0
        },
        "angles": {
          "w": 1.0,
          "x": 0.0,
          "y": 0.0,
          "z": 0.0
        }
      },
      "initCreate": 1,
      "maxNum": 2,
      "objcell_id": 0,
      "probability": 0.26881998777389526,
      "ptid": 0,
      "shade": 0.0,
      "slot": 15,
      "stackSize": -1,
      "type": 23585,
      "whenCreate": 1,
      "whereCreate": 2
    },
    {
      "delay": 1800.0,
      "frame": {
        "origin": {
          "x": 0.0,
          "y": 0.0,
          "z": 0.0
        },
        "angles": {
          "w": 1.0,
          "x": 0.0,
          "y": 0.0,
          "z": 0.0
        }
      },
      "initCreate": 1,
      "maxNum": 2,
      "objcell_id": 0,
      "probability": 0.2981800138950348,
      "ptid": 0,
      "shade": 0.0,
      "slot": 16,
      "stackSize": -1,
      "type": 23491,
      "whenCreate": 1,
      "whereCreate": 2
    },
    {
      "delay": 1800.0,
      "frame": {
        "origin": {
          "x": 0.0,
          "y": 0.0,
          "z": 0.0
        },
        "angles": {
          "w": 1.0,
          "x": 0.0,
          "y": 0.0,
          "z": 0.0
        }
      },
      "initCreate": 1,
      "maxNum": 2,
      "objcell_id": 0,
      "probability": 0.3177199959754944,
      "ptid": 0,
      "shade": 0.0,
      "slot": 17,
      "stackSize": -1,
      "type": 23479,
      "whenCreate": 1,
      "whereCreate": 2
    },
    {
      "delay": 1800.0,
      "frame": {
        "origin": {
          "x": 0.0,
          "y": 0.0,
          "z": 0.0
        },
        "angles": {
          "w": 1.0,
          "x": 0.0,
          "y": 0.0,
          "z": 0.0
        }
      },
      "initCreate": 1,
      "maxNum": 2,
      "objcell_id": 0,
      "probability": 0.33726000785827637,
      "ptid": 0,
      "shade": 0.0,
      "slot": 18,
      "stackSize": -1,
      "type": 23478,
      "whenCreate": 1,
      "whereCreate": 2
    },
    {
      "delay": 1800.0,
      "frame": {
        "origin": {
          "x": 0.0,
          "y": 0.0,
          "z": 0.0
        },
        "angles": {
          "w": 1.0,
          "x": 0.0,
          "y": 0.0,
          "z": 0.0
        }
      },
      "initCreate": 1,
      "maxNum": 2,
      "objcell_id": 0,
      "probability": 0.35679998993873596,
      "ptid": 0,
      "shade": 0.0,
      "slot": 19,
      "stackSize": -1,
      "type": 24276,
      "whenCreate": 1,
      "whereCreate": 2
    },
    {
      "delay": 1800.0,
      "frame": {
        "origin": {
          "x": 0.0,
          "y": 0.0,
          "z": 0.0
        },
        "angles": {
          "w": 1.0,
          "x": 0.0,
          "y": 0.0,
          "z": 0.0
        }
      },
      "initCreate": 1,
      "maxNum": 2,
      "objcell_id": 0,
      "probability": 0.37634000182151794,
      "ptid": 0,
      "shade": 0.0,
      "slot": 20,
      "stackSize": -1,
      "type": 24274,
      "whenCreate": 1,
      "whereCreate": 2
    },
    {
      "delay": 1800.0,
      "frame": {
        "origin": {
          "x": 0.0,
          "y": 0.0,
          "z": 0.0
        },
        "angles": {
          "w": 1.0,
          "x": 0.0,
          "y": 0.0,
          "z": 0.0
        }
      },
      "initCreate": 1,
      "maxNum": 2,
      "objcell_id": 0,
      "probability": 0.4155200123786926,
      "ptid": 0,
      "shade": 0.0,
      "slot": 21,
      "stackSize": -1,
      "type": 24520,
      "whenCreate": 1,
      "whereCreate": 2
    },
    {
      "delay": 1800.0,
      "frame": {
        "origin": {
          "x": 0.0,
          "y": 0.0,
          "z": 0.0
        },
        "angles": {
          "w": 1.0,
          "x": 0.0,
          "y": 0.0,
          "z": 0.0
        }
      },
      "initCreate": 1,
      "maxNum": 2,
      "objcell_id": 0,
      "probability": 0.44488000869750977,
      "ptid": 0,
      "shade": 0.0,
      "slot": 22,
      "stackSize": -1,
      "type": 7139,
      "whenCreate": 1,
      "whereCreate": 2
    },
    {
      "delay": 1800.0,
      "frame": {
        "origin": {
          "x": 0.0,
          "y": 0.0,
          "z": 0.0
        },
        "angles": {
          "w": 1.0,
          "x": 0.0,
          "y": 0.0,
          "z": 0.0
        }
      },
      "initCreate": 1,
      "maxNum": 2,
      "objcell_id": 0,
      "probability": 0.46441999077796936,
      "ptid": 0,
      "shade": 0.0,
      "slot": 23,
      "stackSize": -1,
      "type": 10777,
      "whenCreate": 1,
      "whereCreate": 2
    },
    {
      "delay": 1800.0,
      "frame": {
        "origin": {
          "x": 0.0,
          "y": 0.0,
          "z": 0.0
        },
        "angles": {
          "w": 1.0,
          "x": 0.0,
          "y": 0.0,
          "z": 0.0
        }
      },
      "initCreate": 1,
      "maxNum": 2,
      "objcell_id": 0,
      "probability": 0.4741399884223938,
      "ptid": 0,
      "shade": 0.0,
      "slot": 24,
      "stackSize": -1,
      "type": 10776,
      "whenCreate": 1,
      "whereCreate": 2
    },
    {
      "delay": 1800.0,
      "frame": {
        "origin": {
          "x": 0.0,
          "y": 0.0,
          "z": 0.0
        },
        "angles": {
          "w": 1.0,
          "x": 0.0,
          "y": 0.0,
          "z": 0.0
        }
      },
      "initCreate": 1,
      "maxNum": 2,
      "objcell_id": 0,
      "probability": 0.48385998606681824,
      "ptid": 0,
      "shade": 0.0,
      "slot": 25,
      "stackSize": -1,
      "type": 7091,
      "whenCreate": 1,
      "whereCreate": 2
    },
    {
      "delay": 1800.0,
      "frame": {
        "origin": {
          "x": 0.0,
          "y": 0.0,
          "z": 0.0
        },
        "angles": {
          "w": 1.0,
          "x": 0.0,
          "y": 0.0,
          "z": 0.0
        }
      },
      "initCreate": 1,
      "maxNum": 2,
      "objcell_id": 0,
      "probability": 0.5034000277519226,
      "ptid": 0,
      "shade": 0.0,
      "slot": 26,
      "stackSize": -1,
      "type": 23480,
      "whenCreate": 1,
      "whereCreate": 2
    },
    {
      "delay": 1800.0,
      "frame": {
        "origin": {
          "x": 0.0,
          "y": 0.0,
          "z": 0.0
        },
        "angles": {
          "w": 1.0,
          "x": 0.0,
          "y": 0.0,
          "z": 0.0
        }
      },
      "initCreate": 1,
      "maxNum": 2,
      "objcell_id": 0,
      "probability": 0.5327600240707397,
      "ptid": 0,
      "shade": 0.0,
      "slot": 27,
      "stackSize": -1,
      "type": 23493,
      "whenCreate": 1,
      "whereCreate": 2
    },
    {
      "delay": 1800.0,
      "frame": {
        "origin": {
          "x": 0.0,
          "y": 0.0,
          "z": 0.0
        },
        "angles": {
          "w": 1.0,
          "x": 0.0,
          "y": 0.0,
          "z": 0.0
        }
      },
      "initCreate": 1,
      "maxNum": 1,
      "objcell_id": 0,
      "probability": 0.5474749803543091,
      "ptid": 0,
      "shade": 0.0,
      "slot": 28,
      "stackSize": -1,
      "type": 87049,
      "whenCreate": 1,
      "whereCreate": 2
    },
    {
      "delay": 1800.0,
      "frame": {
        "origin": {
          "x": 0.0,
          "y": 0.0,
          "z": 0.0
        },
        "angles": {
          "w": 1.0,
          "x": 0.0,
          "y": 0.0,
          "z": 0.0
        }
      },
      "initCreate": 1,
      "maxNum": 2,
      "objcell_id": 0,
      "probability": 0.5522000193595886,
      "ptid": 0,
      "shade": 0.0,
      "slot": 29,
      "stackSize": -1,
      "type": 24278,
      "whenCreate": 1,
      "whereCreate": 2
    },
    {
      "delay": 1800.0,
      "frame": {
        "origin": {
          "x": 0.0,
          "y": 0.0,
          "z": 0.0
        },
        "angles": {
          "w": 1.0,
          "x": 0.0,
          "y": 0.0,
          "z": 0.0
        }
      },
      "initCreate": 1,
      "maxNum": 2,
      "objcell_id": 0,
      "probability": 0.5717399716377258,
      "ptid": 0,
      "shade": 0.0,
      "slot": 30,
      "stackSize": -1,
      "type": 24282,
      "whenCreate": 1,
      "whereCreate": 2
    },
    {
      "delay": 1800.0,
      "frame": {
        "origin": {
          "x": 0.0,
          "y": 0.0,
          "z": 0.0
        },
        "angles": {
          "w": 1.0,
          "x": 0.0,
          "y": 0.0,
          "z": 0.0
        }
      },
      "initCreate": 1,
      "maxNum": 2,
      "objcell_id": 0,
      "probability": 0.6011000275611877,
      "ptid": 0,
      "shade": 0.0,
      "slot": 31,
      "stackSize": -1,
      "type": 24522,
      "whenCreate": 1,
      "whereCreate": 2
    },
    {
      "delay": 1800.0,
      "frame": {
        "origin": {
          "x": 0.0,
          "y": 0.0,
          "z": 0.0
        },
        "angles": {
          "w": 1.0,
          "x": 0.0,
          "y": 0.0,
          "z": 0.0
        }
      },
      "initCreate": 1,
      "maxNum": 2,
      "objcell_id": 0,
      "probability": 0.620639979839325,
      "ptid": 0,
      "shade": 0.0,
      "slot": 32,
      "stackSize": -1,
      "type": 14876,
      "whenCreate": 1,
      "whereCreate": 2
    },
    {
      "delay": 1800.0,
      "frame": {
        "origin": {
          "x": 0.0,
          "y": 0.0,
          "z": 0.0
        },
        "angles": {
          "w": 1.0,
          "x": 0.0,
          "y": 0.0,
          "z": 0.0
        }
      },
      "initCreate": 1,
      "maxNum": 2,
      "objcell_id": 0,
      "probability": 0.6401799917221069,
      "ptid": 0,
      "shade": 0.0,
      "slot": 33,
      "stackSize": -1,
      "type": 14514,
      "whenCreate": 1,
      "whereCreate": 2
    },
    {
      "delay": 1800.0,
      "frame": {
        "origin": {
          "x": 0.0,
          "y": 0.0,
          "z": 0.0
        },
        "angles": {
          "w": 1.0,
          "x": 0.0,
          "y": 0.0,
          "z": 0.0
        }
      },
      "initCreate": 1,
      "maxNum": 2,
      "objcell_id": 0,
      "probability": 0.6597200036048889,
      "ptid": 0,
      "shade": 0.0,
      "slot": 34,
      "stackSize": -1,
      "type": 14877,
      "whenCreate": 1,
      "whereCreate": 2
    },
    {
      "delay": 1800.0,
      "frame": {
        "origin": {
          "x": 0.0,
          "y": 0.0,
          "z": 0.0
        },
        "angles": {
          "w": 1.0,
          "x": 0.0,
          "y": 0.0,
          "z": 0.0
        }
      },
      "initCreate": 1,
      "maxNum": 2,
      "objcell_id": 0,
      "probability": 0.6792600154876709,
      "ptid": 0,
      "shade": 0.0,
      "slot": 35,
      "stackSize": -1,
      "type": 7127,
      "whenCreate": 1,
      "whereCreate": 2
    },
    {
      "delay": 1800.0,
      "frame": {
        "origin": {
          "x": 0.0,
          "y": 0.0,
          "z": 0.0
        },
        "angles": {
          "w": 1.0,
          "x": 0.0,
          "y": 0.0,
          "z": 0.0
        }
      },
      "initCreate": 1,
      "maxNum": 2,
      "objcell_id": 0,
      "probability": 0.6988000273704529,
      "ptid": 0,
      "shade": 0.0,
      "slot": 36,
      "stackSize": -1,
      "type": 7125,
      "whenCreate": 1,
      "whereCreate": 2
    },
    {
      "delay": 1800.0,
      "frame": {
        "origin": {
          "x": 0.0,
          "y": 0.0,
          "z": 0.0
        },
        "angles": {
          "w": 1.0,
          "x": 0.0,
          "y": 0.0,
          "z": 0.0
        }
      },
      "initCreate": 1,
      "maxNum": 2,
      "objcell_id": 0,
      "probability": 0.7085199952125549,
      "ptid": 0,
      "shade": 0.0,
      "slot": 37,
      "stackSize": -1,
      "type": 7150,
      "whenCreate": 1,
      "whereCreate": 2
    },
    {
      "delay": 1800.0,
      "frame": {
        "origin": {
          "x": 0.0,
          "y": 0.0,
          "z": 0.0
        },
        "angles": {
          "w": 1.0,
          "x": 0.0,
          "y": 0.0,
          "z": 0.0
        }
      },
      "initCreate": 1,
      "maxNum": 2,
      "objcell_id": 0,
      "probability": 0.7182400226593018,
      "ptid": 0,
      "shade": 0.0,
      "slot": 38,
      "stackSize": -1,
      "type": 36838,
      "whenCreate": 1,
      "whereCreate": 2
    },
    {
      "delay": 1800.0,
      "frame": {
        "origin": {
          "x": 0.0,
          "y": 0.0,
          "z": 0.0
        },
        "angles": {
          "w": 1.0,
          "x": 0.0,
          "y": 0.0,
          "z": 0.0
        }
      },
      "initCreate": 1,
      "maxNum": 2,
      "objcell_id": 0,
      "probability": 0.7279599905014038,
      "ptid": 0,
      "shade": 0.0,
      "slot": 39,
      "stackSize": -1,
      "type": 36837,
      "whenCreate": 1,
      "whereCreate": 2
    },
    {
      "delay": 1800.0,
      "frame": {
        "origin": {
          "x": 0.0,
          "y": 0.0,
          "z": 0.0
        },
        "angles": {
          "w": 1.0,
          "x": 0.0,
          "y": 0.0,
          "z": 0.0
        }
      },
      "initCreate": 1,
      "maxNum": 2,
      "objcell_id": 0,
      "probability": 0.7376800179481506,
      "ptid": 0,
      "shade": 0.0,
      "slot": 40,
      "stackSize": -1,
      "type": 36836,
      "whenCreate": 1,
      "whereCreate": 2
    },
    {
      "delay": 1800.0,
      "frame": {
        "origin": {
          "x": 0.0,
          "y": 0.0,
          "z": 0.0
        },
        "angles": {
          "w": 1.0,
          "x": 0.0,
          "y": 0.0,
          "z": 0.0
        }
      },
      "initCreate": 1,
      "maxNum": 2,
      "objcell_id": 0,
      "probability": 0.7473999857902527,
      "ptid": 0,
      "shade": 0.0,
      "slot": 41,
      "stackSize": -1,
      "type": 24951,
      "whenCreate": 1,
      "whereCreate": 2
    },
    {
      "delay": 1800.0,
      "frame": {
        "origin": {
          "x": 0.0,
          "y": 0.0,
          "z": 0.0
        },
        "angles": {
          "w": 1.0,
          "x": 0.0,
          "y": 0.0,
          "z": 0.0
        }
      },
      "initCreate": 1,
      "maxNum": 2,
      "objcell_id": 0,
      "probability": 0.7767599821090698,
      "ptid": 0,
      "shade": 0.0,
      "slot": 42,
      "stackSize": -1,
      "type": 24524,
      "whenCreate": 1,
      "whereCreate": 2
    },
    {
      "delay": 1800.0,
      "frame": {
        "origin": {
          "x": 0.0,
          "y": 0.0,
          "z": 0.0
        },
        "angles": {
          "w": 1.0,
          "x": 0.0,
          "y": 0.0,
          "z": 0.0
        }
      },
      "initCreate": 1,
      "maxNum": 2,
      "objcell_id": 0,
      "probability": 0.7962999939918518,
      "ptid": 0,
      "shade": 0.0,
      "slot": 43,
      "stackSize": -1,
      "type": 24523,
      "whenCreate": 1,
      "whereCreate": 2
    },
    {
      "delay": 1800.0,
      "frame": {
        "origin": {
          "x": 0.0,
          "y": 0.0,
          "z": 0.0
        },
        "angles": {
          "w": 1.0,
          "x": 0.0,
          "y": 0.0,
          "z": 0.0
        }
      },
      "initCreate": 1,
      "maxNum": 2,
      "objcell_id": 0,
      "probability": 0.8354799747467041,
      "ptid": 0,
      "shade": 0.0,
      "slot": 44,
      "stackSize": -1,
      "type": 23481,
      "whenCreate": 1,
      "whereCreate": 2
    },
    {
      "delay": 1800.0,
      "frame": {
        "origin": {
          "x": 0.0,
          "y": 0.0,
          "z": 0.0
        },
        "angles": {
          "w": 1.0,
          "x": 0.0,
          "y": 0.0,
          "z": 0.0
        }
      },
      "initCreate": 1,
      "maxNum": 2,
      "objcell_id": 0,
      "probability": 0.8746600151062012,
      "ptid": 0,
      "shade": 0.0,
      "slot": 45,
      "stackSize": -1,
      "type": 23497,
      "whenCreate": 1,
      "whereCreate": 2
    },
    {
      "delay": 1800.0,
      "frame": {
        "origin": {
          "x": 0.0,
          "y": 0.0,
          "z": 0.0
        },
        "angles": {
          "w": 1.0,
          "x": 0.0,
          "y": 0.0,
          "z": 0.0
        }
      },
      "initCreate": 1,
      "maxNum": 2,
      "objcell_id": 0,
      "probability": 0.9040200114250183,
      "ptid": 0,
      "shade": 0.0,
      "slot": 46,
      "stackSize": -1,
      "type": 24133,
      "whenCreate": 1,
      "whereCreate": 2
    },
    {
      "delay": 1800.0,
      "frame": {
        "origin": {
          "x": 0.0,
          "y": 0.0,
          "z": 0.0
        },
        "angles": {
          "w": 1.0,
          "x": 0.0,
          "y": 0.0,
          "z": 0.0
        }
      },
      "initCreate": 1,
      "maxNum": 2,
      "objcell_id": 0,
      "probability": 0.9137399792671204,
      "ptid": 0,
      "shade": 0.0,
      "slot": 47,
      "stackSize": -1,
      "type": 7114,
      "whenCreate": 1,
      "whereCreate": 2
    },
    {
      "delay": 1800.0,
      "frame": {
        "origin": {
          "x": 0.0,
          "y": 0.0,
          "z": 0.0
        },
        "angles": {
          "w": 1.0,
          "x": 0.0,
          "y": 0.0,
          "z": 0.0
        }
      },
      "initCreate": 1,
      "maxNum": 2,
      "objcell_id": 0,
      "probability": 0.9430999755859375,
      "ptid": 0,
      "shade": 0.0,
      "slot": 48,
      "stackSize": -1,
      "type": 7166,
      "whenCreate": 1,
      "whereCreate": 2
    },
    {
      "delay": 1800.0,
      "frame": {
        "origin": {
          "x": 0.0,
          "y": 0.0,
          "z": 0.0
        },
        "angles": {
          "w": 1.0,
          "x": 0.0,
          "y": 0.0,
          "z": 0.0
        }
      },
      "initCreate": 1,
      "maxNum": 2,
      "objcell_id": 0,
      "probability": 0.9577299952507019,
      "ptid": 0,
      "shade": 0.0,
      "slot": 49,
      "stackSize": -1,
      "type": 9288,
      "whenCreate": 1,
      "whereCreate": 2
    },
    {
      "delay": 1800.0,
      "frame": {
        "origin": {
          "x": 0.0,
          "y": 0.0,
          "z": 0.0
        },
        "angles": {
          "w": 1.0,
          "x": 0.0,
          "y": 0.0,
          "z": 0.0
        }
      },
      "initCreate": 1,
      "maxNum": 2,
      "objcell_id": 0,
      "probability": 0.9625399708747864,
      "ptid": 0,
      "shade": 0.0,
      "slot": 50,
      "stackSize": -1,
      "type": 9286,
      "whenCreate": 1,
      "whereCreate": 2
    },
    {
      "delay": 1800.0,
      "frame": {
        "origin": {
          "x": 0.0,
          "y": 0.0,
          "z": 0.0
        },
        "angles": {
          "w": 1.0,
          "x": 0.0,
          "y": 0.0,
          "z": 0.0
        }
      },
      "initCreate": 1,
      "maxNum": 1,
      "objcell_id": 0,
      "probability": 0.9722599983215332,
      "ptid": 0,
      "shade": 0.0,
      "slot": 51,
      "stackSize": -1,
      "type": 22732,
      "whenCreate": 1,
      "whereCreate": 2
    },
    {
      "delay": 1800.0,
      "frame": {
        "origin": {
          "x": 0.0,
          "y": 0.0,
          "z": 0.0
        },
        "angles": {
          "w": 1.0,
          "x": 0.0,
          "y": 0.0,
          "z": 0.0
        }
      },
      "initCreate": 1,
      "maxNum": 1,
      "objcell_id": 0,
      "probability": 0.9811599850654602,
      "ptid": 0,
      "shade": 0.0,
      "slot": 52,
      "stackSize": -1,
      "type": 31688,
      "whenCreate": 1,
      "whereCreate": 2
    },
    {
      "delay": 1800.0,
      "frame": {
        "origin": {
          "x": 0.0,
          "y": 0.0,
          "z": 0.0
        },
        "angles": {
          "w": 1.0,
          "x": 0.0,
          "y": 0.0,
          "z": 0.0
        }
      },
      "initCreate": 1,
      "maxNum": 1,
      "objcell_id": 0,
      "probability": 0.9900599718093872,
      "ptid": 0,
      "shade": 0.0,
      "slot": 53,
      "stackSize": -1,
      "type": 70018,
      "whenCreate": 1,
      "whereCreate": 2
    },
    {
      "delay": 1800.0,
      "frame": {
        "origin": {
          "x": 0.0,
          "y": 0.0,
          "z": 0.0
        },
        "angles": {
          "w": 1.0,
          "x": 0.0,
          "y": 0.0,
          "z": 0.0
        }
      },
      "initCreate": 1,
      "maxNum": 1,
      "objcell_id": 0,
      "probability": 1.0,
      "ptid": 0,
      "shade": 0.0,
      "slot": 54,
      "stackSize": -1,
      "type": 41004,
      "whenCreate": 1,
      "whereCreate": 2
    }
  ],
  "changelog": [
    {
      "created": "2023-07-12T21:56:57.5416461Z",
      "author": "ACE.Adapter",
      "comment": "Weenie exported from ACEmulator world database using ACE.Adapter"
    }
  ],
  "isDone": false
}