{
  "wcid": 22020,
  "weenieType": 2,
  "boolStats": [
    {
      "key": 22,
      "value": 1
    },
    {
      "key": 23,
      "value": 1
    }
  ],
  "intStats": [
    {
      "key": 1,
      "value": 4
    },
    {
      "key": 3,
      "value": 4
    },
    {
      "key": 4,
      "value": 81664
    },
    {
      "key": 5,
      "value": 1400
    },
    {
      "key": 8,
      "value": 150
    },
    {
      "key": 9,
      "value": 32512
    },
    {
      "key": 16,
      "value": 1
    },
    {
      "key": 19,
      "value": 1000
    },
    {
      "key": 27,
      "value": 1
    },
    {
      "key": 28,
      "value": 10
    },
    {
      "key": 93,
      "value": 1044
    },
    {
      "key": 150,
      "value": 103
    },
    {
      "key": 151,
      "value": 2
    }
  ],
  "didStats": [
    {
      "key": 1,
      "value": 33558008
    },
    {
      "key": 3,
      "value": 536870932
    },
    {
      "key": 6,
      "value": 67108990
    },
    {
      "key": 7,
      "value": 268436470
    },
    {
      "key": 8,
      "value": 100673718
    },
    {
      "key": 22,
      "value": 872415275
    },
    {
      "key": 36,
      "value": 234881046
    }
  ],
  "iidStats": [],
  "floatStats": [
    {
      "key": 12,
      "value": 0.0
    },
    {
      "key": 13,
      "value": 0.5
    },
    {
      "key": 14,
      "value": 0.5
    },
    {
      "key": 15,
      "value": 0.75
    },
    {
      "key": 16,
      "value": 0.65
    },
    {
      "key": 17,
      "value": 0.55
    },
    {
      "key": 18,
      "value": 0.55
    },
    {
      "key": 19,
      "value": 0.65
    },
    {
      "key": 39,
      "value": 0.8
    }
  ],
  "int64Stats": [],
  "stringStats": [
    {
      "key": 1,
      "value": "Skeletal Guise"
    },
    {
      "key": 15,
      "value": "A skeleton costume."
    },
    {
      "key": 16,
      "value": "A finely crafted skeleton costume that is only missing the head."
    }
  ],
  "changelog": [
    {
      "created": "2023-07-12T22:04:43.133704Z",
      "author": "ACE.Adapter",
      "comment": "Weenie exported from ACEmulator world database using ACE.Adapter"
    }
  ],
  "isDone": false
}