{
  "wcid": 24110,
  "weenieType": 8,
  "pageDataList": {
    "maxNumCharsPerPage": 1000,
    "maxNumPages": 3,
    "pages": [
      {
        "authorAccount": "prewritten",
        "authorID": 4294967295,
        "authorName": "Lord Asheron",
        "ignoreAuthor": 0,
        "pageText": "Emperor Kellin has placed a garrison within the walls of Knorr. This is the first instance that there have been any within these walls that did not earn their way through without solving the riddles. I have underestimated Gaerlan's resolve in being allowed to attend our off world visits. Never had I thought that he would entreat the ear of the Emperor and use time granted to explicate the inner workings of this Lyceum. Nevertheless, until I can unshoulder my burden I must make whatever amends are necessary to ensure that the sacrifice of the five is not unhinged.\n"
      },
      {
        "authorAccount": "prewritten",
        "authorID": 4294967295,
        "authorName": "Lord Asheron",
        "ignoreAuthor": 0,
        "pageText": "I have given them residence within the Caerlin Dormitory, apart from my personal guard. The Emperor was fair in his insistence and allowed me the courtesy of keeping the Order of Perfect Light as the main force of defense of the Lyceum. Though he now knows my secret I have surmised that he fears me more now than he has before and as such he might be willing to extend an arm to test my resolve but he has yet to strike at me.\n\nHis forces will accompany us when we make our next trip to another world. The ritual will began on the first day of \n"
      },
      {
        "authorAccount": "prewritten",
        "authorID": 4294967295,
        "authorName": "Lord Asheron",
        "ignoreAuthor": 0,
        "pageText": "ascendance of both Rez'arel and Alb'arel.\n"
      }
    ]
  },
  "boolStats": [
    {
      "key": 22,
      "value": 0
    }
  ],
  "intStats": [
    {
      "key": 1,
      "value": 8192
    },
    {
      "key": 5,
      "value": 160
    },
    {
      "key": 8,
      "value": 200
    },
    {
      "key": 9,
      "value": 0
    },
    {
      "key": 16,
      "value": 8
    },
    {
      "key": 19,
      "value": 90
    },
    {
      "key": 37,
      "value": 50
    },
    {
      "key": 93,
      "value": 1044
    }
  ],
  "didStats": [
    {
      "key": 1,
      "value": 33556929
    },
    {
      "key": 3,
      "value": 536870932
    },
    {
      "key": 8,
      "value": 100671237
    },
    {
      "key": 22,
      "value": 872415275
    }
  ],
  "iidStats": [],
  "floatStats": [
    {
      "key": 39,
      "value": 1.22
    }
  ],
  "int64Stats": [],
  "stringStats": [
    {
      "key": 1,
      "value": "Personal Entry, Arrival of Kellin's Troops"
    }
  ],
  "changelog": [
    {
      "created": "2023-07-12T22:05:28.2234265Z",
      "author": "ACE.Adapter",
      "comment": "Weenie exported from ACEmulator world database using ACE.Adapter"
    }
  ],
  "isDone": false
}