{
  "wcid": 38583,
  "weenieType": 7,
  "boolStats": [
    {
      "key": 1,
      "value": 1
    }
  ],
  "intStats": [
    {
      "key": 1,
      "value": 65536
    },
    {
      "key": 16,
      "value": 32
    },
    {
      "key": 93,
      "value": 3084
    },
    {
      "key": 111,
      "value": 49
    },
    {
      "key": 133,
      "value": 4
    }
  ],
  "didStats": [
    {
      "key": 1,
      "value": 33555925
    },
    {
      "key": 2,
      "value": 150994947
    },
    {
      "key": 8,
      "value": 100667499
    }
  ],
  "iidStats": [],
  "floatStats": [
    {
      "key": 54,
      "value": -0.1
    }
  ],
  "int64Stats": [],
  "stringStats": [
    {
      "key": 1,
      "value": "Chamber of the High Priest's Second"
    },
    {
      "key": 37,
      "value": "HighPriestThirdDead"
    }
  ],
  "posStats": [
    {
      "key": 2,
      "value": {
        "frame": {
          "origin": {
            "x": 9.40494,
            "y": -120.053,
            "z": 0.005
          },
          "angles": {
            "w": 0.6967,
            "x": 0.0,
            "y": 0.0,
            "z": -0.717356
          }
        },
        "objcell_id": 14483718
      }
    }
  ],
  "changelog": [
    {
      "created": "2023-07-12T22:09:26.6288092Z",
      "author": "ACE.Adapter",
      "comment": "Weenie exported from ACEmulator world database using ACE.Adapter"
    }
  ],
  "isDone": false
}