{
  "wcid": 43860,
  "weenieType": 10,
  "attributes": {
    "strength": {
      "cp_spent": 0,
      "level_from_cp": 0,
      "init_level": 600
    },
    "endurance": {
      "cp_spent": 0,
      "level_from_cp": 0,
      "init_level": 620
    },
    "coordination": {
      "cp_spent": 0,
      "level_from_cp": 0,
      "init_level": 300
    },
    "quickness": {
      "cp_spent": 0,
      "level_from_cp": 0,
      "init_level": 400
    },
    "focus": {
      "cp_spent": 0,
      "level_from_cp": 0,
      "init_level": 400
    },
    "self": {
      "cp_spent": 0,
      "level_from_cp": 0,
      "init_level": 400
    },
    "health": {
      "cp_spent": 0,
      "level_from_cp": 0,
      "init_level": 19690,
      "current": 20000
    },
    "stamina": {
      "cp_spent": 0,
      "level_from_cp": 0,
      "init_level": 4380,
      "current": 5000
    },
    "mana": {
      "cp_spent": 0,
      "level_from_cp": 0,
      "init_level": 2600,
      "current": 3000
    }
  },
  "boolStats": [
    {
      "key": 1,
      "value": 1
    },
    {
      "key": 19,
      "value": 0
    }
  ],
  "intStats": [
    {
      "key": 1,
      "value": 16
    },
    {
      "key": 2,
      "value": 22
    },
    {
      "key": 3,
      "value": 39
    },
    {
      "key": 6,
      "value": -1
    },
    {
      "key": 7,
      "value": -1
    },
    {
      "key": 16,
      "value": 32
    },
    {
      "key": 25,
      "value": 600
    },
    {
      "key": 93,
      "value": 6292504
    },
    {
      "key": 95,
      "value": 8
    },
    {
      "key": 133,
      "value": 4
    },
    {
      "key": 134,
      "value": 16
    }
  ],
  "didStats": [
    {
      "key": 1,
      "value": 33556251
    },
    {
      "key": 2,
      "value": 150995091
    },
    {
      "key": 3,
      "value": 536870914
    },
    {
      "key": 6,
      "value": 67108990
    },
    {
      "key": 7,
      "value": 268435871
    },
    {
      "key": 8,
      "value": 100670398
    }
  ],
  "iidStats": [],
  "floatStats": [
    {
      "key": 39,
      "value": 1.2
    },
    {
      "key": 54,
      "value": 3.0
    }
  ],
  "int64Stats": [],
  "stringStats": [
    {
      "key": 1,
      "value": "Black Ferah"
    }
  ],
  "createList": [
    {
      "wcid": 2630,
      "palette": 88,
      "shade": 0.0,
      "destination": 2,
      "stack_size": 0,
      "try_to_bond": 0
    }
  ],
  "emoteTable": [
    {
      "key": 1,
      "value": [
        {
          "category": 1,
          "emotes": [
            {
              "type": 12,
              "delay": 0.0,
              "extent": 1.0
            },
            {
              "type": 30,
              "delay": 0.0,
              "extent": 1.0,
              "msg": "ShadowInvasion@3-3_13",
              "max": 3,
              "min": 3
            }
          ],
          "probability": 1.0,
          "classID": 72858
        },
        {
          "category": 1,
          "emotes": [
            {
              "type": 30,
              "delay": 0.0,
              "extent": 1.0,
              "msg": "ShadowInvasion@1-1_12",
              "max": 1,
              "min": 1
            }
          ],
          "probability": 1.0,
          "classID": 43859
        },
        {
          "category": 1,
          "emotes": [
            {
              "type": 12,
              "delay": 0.0,
              "extent": 1.0
            },
            {
              "type": 10,
              "delay": 0.0,
              "extent": 1.0,
              "msg": "I don't have time for such things right now. Bring it to Ler Rhan. I'm sure he can pull some useful information from it."
            }
          ],
          "probability": 1.0,
          "classID": 43894
        }
      ]
    },
    {
      "key": 7,
      "value": [
        {
          "category": 7,
          "emotes": [
            {
              "type": 12,
              "delay": 0.0,
              "extent": 1.0
            },
            {
              "type": 21,
              "delay": 0.0,
              "extent": 1.0,
              "msg": "ShadowInvasionWait@15"
            }
          ],
          "probability": 1.0
        }
      ]
    },
    {
      "key": 12,
      "value": [
        {
          "category": 12,
          "emotes": [
            {
              "type": 67,
              "delay": 0.0,
              "extent": 1.0,
              "msg": "OnCooldown"
            }
          ],
          "probability": 1.0,
          "quest": "ShadowInvasionWait@15"
        },
        {
          "category": 12,
          "emotes": [
            {
              "type": 21,
              "delay": 0.0,
              "extent": 1.0,
              "msg": "ShadowVortexDule"
            }
          ],
          "probability": 1.0,
          "quest": "ShadowInvasion@5-5_11"
        },
        {
          "category": 12,
          "emotes": [
            {
              "type": 10,
              "delay": 0.0,
              "extent": 1.0,
              "msg": "I see you have chosen to side with Isin Dule. Be gone."
            }
          ],
          "probability": 1.0,
          "quest": "ShadowVortexDule"
        },
        {
          "category": 12,
          "emotes": [
            {
              "type": 21,
              "delay": 0.0,
              "extent": 1.0,
              "msg": "KillTaskSoldier@KillTaskCompleted"
            }
          ],
          "probability": 1.0,
          "quest": "KillTaskSoldier@KillTaskInProgress"
        },
        {
          "category": 12,
          "emotes": [
            {
              "type": 22,
              "delay": 0.0,
              "extent": 1.0,
              "msg": "ShadowInvasion"
            },
            {
              "type": 22,
              "delay": 0.0,
              "extent": 1.0,
              "msg": "ShadowInvasionWait"
            },
            {
              "type": 31,
              "delay": 0.0,
              "extent": 1.0,
              "msg": "KillTaskSoldier"
            },
            {
              "type": 31,
              "delay": 0.0,
              "extent": 1.0,
              "msg": "ShadowVortexFerah"
            },
            {
              "type": 10,
              "delay": 0.0,
              "extent": 1.0,
              "msg": "Isin Dule's forces left with their tails between their legs."
            },
            {
              "type": 10,
              "delay": 0.0,
              "extent": 1.0,
              "msg": "Ler Rhan will be pleased, the last phase of the plan is almost ready..."
            },
            {
              "type": 62,
              "delay": 0.0,
              "extent": 1.0,
              "amount64": 350000000,
              "heroxp64": 0
            },
            {
              "type": 113,
              "delay": 0.0,
              "extent": 1.0,
              "amount64": 30000
            },
            {
              "type": 18,
              "delay": 0.0,
              "extent": 1.0,
              "msg": "You have been awarded the title of Soul Siphon."
            },
            {
              "type": 34,
              "delay": 0.0,
              "extent": 1.0,
              "amount": 730
            },
            {
              "type": 3,
              "delay": 0.0,
              "extent": 1.0,
              "cprof": {
                "wcid": 38919,
                "palette": 0,
                "shade": 0.0,
                "destination": 0,
                "stack_size": 1,
                "try_to_bond": 0
              }
            }
          ],
          "probability": 1.0,
          "quest": "KillTaskSoldier@KillTaskCompleted"
        },
        {
          "category": 12,
          "emotes": [
            {
              "type": 21,
              "delay": 0.0,
              "extent": 1.0,
              "msg": "ShadowAssaultDule"
            }
          ],
          "probability": 1.0,
          "quest": "ShadowInvasion@4-4_8"
        },
        {
          "category": 12,
          "emotes": [
            {
              "type": 10,
              "delay": 0.0,
              "extent": 1.0,
              "msg": "I suggest you leave this place."
            }
          ],
          "probability": 1.0,
          "quest": "ShadowAssaultDule"
        },
        {
          "category": 12,
          "emotes": [
            {
              "type": 22,
              "delay": 0.0,
              "extent": 1.0,
              "msg": "DarkRecordingsStart"
            },
            {
              "type": 10,
              "delay": 0.0,
              "extent": 1.0,
              "msg": "Ler Rhan says we need as many people collecting ley line data as we can get."
            },
            {
              "type": 10,
              "delay": 0.0,
              "extent": 1.0,
              "msg": "It is a simple task, so even you shouldn't be able to screw it up."
            },
            {
              "type": 10,
              "delay": 0.0,
              "extent": 1.0,
              "msg": "Some of the previous inept workers left pieces of the Recording Device in several caves around here."
            },
            {
              "type": 10,
              "delay": 0.0,
              "extent": 1.0,
              "msg": "Collect the pieces and assemble the device. Then use that device at the two locations marked by the dark stones."
            },
            {
              "type": 10,
              "delay": 0.0,
              "extent": 1.0,
              "msg": "Return to me with the information you've collected."
            }
          ],
          "probability": 1.0,
          "quest": "ShadowInvasion@3-3_12"
        },
        {
          "category": 12,
          "emotes": [
            {
              "type": 10,
              "delay": 0.0,
              "extent": 1.0,
              "msg": "We are still working with the data you collected."
            }
          ],
          "probability": 1.0,
          "quest": "ShadowInvasion@4-4_9"
        },
        {
          "category": 12,
          "emotes": [
            {
              "type": 10,
              "delay": 0.0,
              "extent": 1.0,
              "msg": "I already received the communication. I have no further use for you. Be gone."
            }
          ],
          "probability": 1.0,
          "quest": "ShadowInvasion@1-1_11"
        },
        {
          "category": 12,
          "emotes": [
            {
              "type": 21,
              "delay": 0.0,
              "extent": 1.0,
              "msg": "DarkRecording1@5"
            }
          ],
          "probability": 1.0,
          "quest": "ShadowInvasion@3-3_13"
        },
        {
          "category": 12,
          "emotes": [
            {
              "type": 21,
              "delay": 0.0,
              "extent": 1.0,
              "msg": "DarkRecording2@5"
            }
          ],
          "probability": 1.0,
          "quest": "DarkRecording1@5"
        },
        {
          "category": 12,
          "emotes": [
            {
              "type": 21,
              "delay": 0.0,
              "extent": 1.0,
              "msg": "DarkRecordingFalse@4"
            }
          ],
          "probability": 1.0,
          "quest": "DarkRecording2@5"
        },
        {
          "category": 12,
          "emotes": [
            {
              "type": 22,
              "delay": 0.0,
              "extent": 1.0,
              "msg": "ShadowInvasion"
            },
            {
              "type": 22,
              "delay": 0.0,
              "extent": 1.0,
              "msg": "DuleCounter"
            },
            {
              "type": 22,
              "delay": 0.0,
              "extent": 1.0,
              "msg": "ShadowInvasionWait"
            },
            {
              "type": 31,
              "delay": 0.0,
              "extent": 1.0,
              "msg": "DarkRecording1"
            },
            {
              "type": 31,
              "delay": 0.0,
              "extent": 1.0,
              "msg": "DarkRecording2"
            },
            {
              "type": 31,
              "delay": 0.0,
              "extent": 1.0,
              "msg": "DarkRecordingFalse"
            },
            {
              "type": 31,
              "delay": 0.0,
              "extent": 1.0,
              "msg": "DarkRecordingsStart"
            },
            {
              "type": 10,
              "delay": 0.0,
              "extent": 1.0,
              "msg": "You've collected the data?"
            },
            {
              "type": 10,
              "delay": 0.0,
              "extent": 1.0,
              "msg": "Let me have a look."
            },
            {
              "type": 18,
              "delay": 0.0,
              "extent": 1.0,
              "msg": "Black Ferah looks over the data quickly."
            },
            {
              "type": 10,
              "delay": 0.0,
              "extent": 1.0,
              "msg": "Very odd, this data conflicts some of our early tests."
            },
            {
              "type": 18,
              "delay": 0.0,
              "extent": 1.0,
              "msg": "Black Ferah eyes you wearily."
            },
            {
              "type": 10,
              "delay": 0.0,
              "extent": 1.0,
              "msg": "Are you sure you conducted the tests correctly?"
            },
            {
              "type": 10,
              "delay": 0.0,
              "extent": 1.0,
              "msg": "Never mind, I will send someone else out to reverify the results."
            },
            {
              "type": 74,
              "delay": 0.0,
              "extent": 1.0,
              "cprof": {
                "wcid": 72858,
                "palette": 0,
                "shade": 0.0,
                "destination": 0,
                "stack_size": -1,
                "try_to_bond": 0
              }
            },
            {
              "type": 74,
              "delay": 0.0,
              "extent": 1.0,
              "cprof": {
                "wcid": 72854,
                "palette": 0,
                "shade": 0.0,
                "destination": 0,
                "stack_size": -1,
                "try_to_bond": 0
              }
            },
            {
              "type": 74,
              "delay": 0.0,
              "extent": 1.0,
              "cprof": {
                "wcid": 72855,
                "palette": 0,
                "shade": 0.0,
                "destination": 0,
                "stack_size": -1,
                "try_to_bond": 0
              }
            },
            {
              "type": 74,
              "delay": 0.0,
              "extent": 1.0,
              "cprof": {
                "wcid": 72856,
                "palette": 0,
                "shade": 0.0,
                "destination": 0,
                "stack_size": -1,
                "try_to_bond": 0
              }
            },
            {
              "type": 74,
              "delay": 0.0,
              "extent": 1.0,
              "cprof": {
                "wcid": 72857,
                "palette": 0,
                "shade": 0.0,
                "destination": 0,
                "stack_size": -1,
                "try_to_bond": 0
              }
            },
            {
              "type": 62,
              "delay": 0.0,
              "extent": 1.0,
              "amount64": 350000000,
              "heroxp64": 0
            },
            {
              "type": 113,
              "delay": 0.0,
              "extent": 1.0,
              "amount64": 30000
            },
            {
              "type": 18,
              "delay": 0.0,
              "extent": 1.0,
              "msg": "You have been awarded the title of Searching the Shadows."
            },
            {
              "type": 34,
              "delay": 0.0,
              "extent": 1.0,
              "amount": 726
            },
            {
              "type": 3,
              "delay": 0.0,
              "extent": 1.0,
              "cprof": {
                "wcid": 38919,
                "palette": 0,
                "shade": 0.0,
                "destination": 0,
                "stack_size": 1,
                "try_to_bond": 0
              }
            }
          ],
          "probability": 1.0,
          "quest": "DarkRecordingFalse@4"
        },
        {
          "category": 12,
          "emotes": [
            {
              "type": 10,
              "delay": 0.0,
              "extent": 1.0,
              "msg": "I already received the communication. I have no further use for you. Be gone."
            }
          ],
          "probability": 1.0,
          "quest": "ShadowInvasion@1-1_12"
        },
        {
          "category": 12,
          "emotes": [
            {
              "type": 22,
              "delay": 0.0,
              "extent": 1.0,
              "msg": "DuleCounter"
            },
            {
              "type": 31,
              "delay": 0.0,
              "extent": 1.0,
              "msg": "DuleInformant"
            },
            {
              "type": 10,
              "delay": 0.0,
              "extent": 1.0,
              "msg": "I have no further need for you. Leave this area and don't confuse that with a suggestion."
            },
            {
              "type": 62,
              "delay": 0.0,
              "extent": 1.0,
              "amount64": 350000000,
              "heroxp64": 0
            },
            {
              "type": 113,
              "delay": 0.0,
              "extent": 1.0,
              "amount64": 30000
            },
            {
              "type": 18,
              "delay": 0.0,
              "extent": 1.0,
              "msg": "You have been awarded the title of Guiding Light."
            },
            {
              "type": 34,
              "delay": 0.0,
              "extent": 1.0,
              "amount": 714
            },
            {
              "type": 3,
              "delay": 0.0,
              "extent": 1.0,
              "cprof": {
                "wcid": 38919,
                "palette": 0,
                "shade": 0.0,
                "destination": 0,
                "stack_size": 1,
                "try_to_bond": 0
              }
            }
          ],
          "probability": 1.0,
          "quest": "DuleInformant@4"
        }
      ]
    },
    {
      "key": 13,
      "value": [
        {
          "category": 13,
          "emotes": [
            {
              "type": 67,
              "delay": 0.0,
              "extent": 1.0,
              "msg": "Check5"
            }
          ],
          "probability": 1.0,
          "quest": "ShadowInvasionWait@15"
        },
        {
          "category": 13,
          "emotes": [
            {
              "type": 22,
              "delay": 0.0,
              "extent": 1.0,
              "msg": "ShadowVortexFerah"
            },
            {
              "type": 30,
              "delay": 0.0,
              "extent": 1.0,
              "msg": "KillTaskSoldier@KillTaskInProgress",
              "max": 15,
              "min": 1
            }
          ],
          "probability": 1.0,
          "quest": "ShadowVortexDule"
        },
        {
          "category": 13,
          "emotes": [
            {
              "type": 18,
              "delay": 0.0,
              "extent": 1.0,
              "msg": "You've killed %tqc out of %tqm Soldiers."
            },
            {
              "type": 10,
              "delay": 0.0,
              "extent": 1.0,
              "msg": "Return after you have killed %tqm Soldiers."
            }
          ],
          "probability": 1.0,
          "quest": "KillTaskSoldier@KillTaskCompleted"
        },
        {
          "category": 13,
          "emotes": [
            {
              "type": 10,
              "delay": 0.0,
              "extent": 1.0,
              "msg": "You must rid Tou-Tou of Isin Dule's forces."
            },
            {
              "type": 10,
              "delay": 0.0,
              "extent": 1.0,
              "msg": "It is not of your concern what is happening at Tou-Tou. You have one purpose for your sad life and that is to do what you are told."
            },
            {
              "type": 70,
              "delay": 0.0,
              "extent": 1.0,
              "amount": 0,
              "msg": "KillTaskSoldier"
            }
          ],
          "probability": 1.0,
          "quest": "KillTaskSoldier@KillTaskInProgress"
        },
        {
          "category": 13,
          "emotes": [
            {
              "type": 67,
              "delay": 0.0,
              "extent": 1.0,
              "msg": "Check4"
            }
          ],
          "probability": 1.0,
          "quest": "ShadowInvasion@5-5_11"
        },
        {
          "category": 13,
          "emotes": [
            {
              "type": 22,
              "delay": 0.0,
              "extent": 1.0,
              "msg": "TalkShadowCaptain"
            },
            {
              "type": 10,
              "delay": 0.0,
              "extent": 1.0,
              "msg": "We have setup forces at the edge of town."
            },
            {
              "type": 10,
              "delay": 0.0,
              "extent": 1.0,
              "msg": "Find the Shadow Captain and provide her with any assistance she needs."
            }
          ],
          "probability": 1.0,
          "quest": "ShadowAssaultDule"
        },
        {
          "category": 13,
          "emotes": [
            {
              "type": 67,
              "delay": 0.0,
              "extent": 1.0,
              "msg": "Check3"
            }
          ],
          "probability": 1.0,
          "quest": "ShadowInvasion@4-4_8"
        },
        {
          "category": 13,
          "emotes": [
            {
              "type": 10,
              "delay": 0.0,
              "extent": 1.0,
              "msg": "I suggest you leave this place."
            }
          ],
          "probability": 1.0,
          "quest": "ShadowInvasion@3-3_12"
        },
        {
          "category": 13,
          "emotes": [
            {
              "type": 30,
              "delay": 0.0,
              "extent": 1.0,
              "msg": "ShadowInvasion@1-1_11",
              "max": 1,
              "min": 1
            }
          ],
          "probability": 1.0,
          "quest": "ShadowInvasion@4-4_9"
        },
        {
          "category": 13,
          "emotes": [
            {
              "type": 10,
              "delay": 0.0,
              "extent": 1.0,
              "msg": "I suggest you leave this place."
            }
          ],
          "probability": 1.0,
          "quest": "ShadowInvasion@1-1_11"
        },
        {
          "category": 13,
          "emotes": [
            {
              "type": 22,
              "delay": 0.0,
              "extent": 1.0,
              "msg": "ShadowInvasion"
            },
            {
              "type": 22,
              "delay": 0.0,
              "extent": 1.0,
              "msg": "ShadowInvasionWait"
            },
            {
              "type": 31,
              "delay": 0.0,
              "extent": 1.0,
              "msg": "DarkRecording1"
            },
            {
              "type": 31,
              "delay": 0.0,
              "extent": 1.0,
              "msg": "DarkRecording2"
            },
            {
              "type": 31,
              "delay": 0.0,
              "extent": 1.0,
              "msg": "DarkRecordingsStart"
            },
            {
              "type": 10,
              "delay": 0.0,
              "extent": 1.0,
              "msg": "You've collected the data?"
            },
            {
              "type": 10,
              "delay": 0.0,
              "extent": 1.0,
              "msg": "Let me have a look."
            },
            {
              "type": 18,
              "delay": 0.0,
              "extent": 1.0,
              "msg": "Black Ferah looks over the data quickly."
            },
            {
              "type": 10,
              "delay": 0.0,
              "extent": 1.0,
              "msg": "Very nice, this data confirms some of our early tests."
            },
            {
              "type": 10,
              "delay": 0.0,
              "extent": 1.0,
              "msg": "I will pass this data on to Ler Rhan."
            },
            {
              "type": 74,
              "delay": 0.0,
              "extent": 1.0,
              "cprof": {
                "wcid": 72858,
                "palette": 0,
                "shade": 0.0,
                "destination": 0,
                "stack_size": -1,
                "try_to_bond": 0
              }
            },
            {
              "type": 74,
              "delay": 0.0,
              "extent": 1.0,
              "cprof": {
                "wcid": 72854,
                "palette": 0,
                "shade": 0.0,
                "destination": 0,
                "stack_size": -1,
                "try_to_bond": 0
              }
            },
            {
              "type": 74,
              "delay": 0.0,
              "extent": 1.0,
              "cprof": {
                "wcid": 72855,
                "palette": 0,
                "shade": 0.0,
                "destination": 0,
                "stack_size": -1,
                "try_to_bond": 0
              }
            },
            {
              "type": 74,
              "delay": 0.0,
              "extent": 1.0,
              "cprof": {
                "wcid": 72856,
                "palette": 0,
                "shade": 0.0,
                "destination": 0,
                "stack_size": -1,
                "try_to_bond": 0
              }
            },
            {
              "type": 74,
              "delay": 0.0,
              "extent": 1.0,
              "cprof": {
                "wcid": 72857,
                "palette": 0,
                "shade": 0.0,
                "destination": 0,
                "stack_size": -1,
                "try_to_bond": 0
              }
            },
            {
              "type": 62,
              "delay": 0.0,
              "extent": 1.0,
              "amount64": 350000000,
              "heroxp64": 0
            },
            {
              "type": 113,
              "delay": 0.0,
              "extent": 1.0,
              "amount64": 30000
            },
            {
              "type": 18,
              "delay": 0.0,
              "extent": 1.0,
              "msg": "You have been awarded the title of In the Dark."
            },
            {
              "type": 34,
              "delay": 0.0,
              "extent": 1.0,
              "amount": 724
            },
            {
              "type": 3,
              "delay": 0.0,
              "extent": 1.0,
              "cprof": {
                "wcid": 38919,
                "palette": 0,
                "shade": 0.0,
                "destination": 0,
                "stack_size": 1,
                "try_to_bond": 0
              }
            }
          ],
          "probability": 1.0,
          "quest": "DarkRecordingFalse@4"
        },
        {
          "category": 13,
          "emotes": [
            {
              "type": 10,
              "delay": 0.0,
              "extent": 1.0,
              "msg": "That is nice and all, but I asked you to collect data with the device, not just bring it to me."
            },
            {
              "type": 10,
              "delay": 0.0,
              "extent": 1.0,
              "msg": "I wonder what Ler Rhan sees in you."
            }
          ],
          "probability": 1.0,
          "quest": "DarkRecording2@5"
        },
        {
          "category": 13,
          "emotes": [
            {
              "type": 10,
              "delay": 0.0,
              "extent": 1.0,
              "msg": "That is nice and all, but I asked you to collect data with the device, not just bring it to me."
            },
            {
              "type": 10,
              "delay": 0.0,
              "extent": 1.0,
              "msg": "I wonder what Ler Rhan sees in you."
            }
          ],
          "probability": 1.0,
          "quest": "DarkRecording1@5"
        },
        {
          "category": 13,
          "emotes": [
            {
              "type": 10,
              "delay": 0.0,
              "extent": 1.0,
              "msg": "I suggest you leave this place."
            }
          ],
          "probability": 1.0,
          "quest": "ShadowInvasion@3-3_13"
        },
        {
          "category": 13,
          "emotes": [
            {
              "type": 74,
              "delay": 0.0,
              "extent": 1.0,
              "cprof": {
                "wcid": 43859,
                "palette": 0,
                "shade": 0.0,
                "destination": 0,
                "stack_size": 1,
                "try_to_bond": 0
              }
            },
            {
              "type": 22,
              "delay": 0.0,
              "extent": 1.0,
              "msg": "ShadowInvasion"
            },
            {
              "type": 22,
              "delay": 0.0,
              "extent": 1.0,
              "msg": "ShadowInvasionWait"
            },
            {
              "type": 10,
              "delay": 0.0,
              "extent": 1.0,
              "msg": "So Ler Rhan wants us to hold our attack for now. I have to wonder what he is waiting for, but I trust his lead on this."
            },
            {
              "type": 21,
              "delay": 0.0,
              "extent": 1.0,
              "msg": "DuleInformant@4"
            }
          ],
          "probability": 1.0,
          "quest": "ShadowInvasion@1-1_12"
        },
        {
          "category": 13,
          "emotes": [
            {
              "type": 10,
              "delay": 0.0,
              "extent": 1.0,
              "msg": "I have no further need for you. If you keep up this kind of loyalty then perhaps we can use you in our ranks when the time comes."
            },
            {
              "type": 62,
              "delay": 0.0,
              "extent": 1.0,
              "amount64": 350000000,
              "heroxp64": 0
            },
            {
              "type": 113,
              "delay": 0.0,
              "extent": 1.0,
              "amount64": 30000
            },
            {
              "type": 18,
              "delay": 0.0,
              "extent": 1.0,
              "msg": "You have been awarded the title of Clouded Soul."
            },
            {
              "type": 34,
              "delay": 0.0,
              "extent": 1.0,
              "amount": 715
            },
            {
              "type": 3,
              "delay": 0.0,
              "extent": 1.0,
              "cprof": {
                "wcid": 38919,
                "palette": 0,
                "shade": 0.0,
                "destination": 0,
                "stack_size": 1,
                "try_to_bond": 0
              }
            }
          ],
          "probability": 1.0,
          "quest": "DuleInformant@4"
        }
      ]
    },
    {
      "key": 32,
      "value": [
        {
          "category": 32,
          "emotes": [
            {
              "type": 30,
              "delay": 0.0,
              "extent": 1.0,
              "msg": "ShadowInvasion@5-5_11",
              "max": 5,
              "min": 5
            }
          ],
          "probability": 1.0,
          "quest": "Check5"
        },
        {
          "category": 32,
          "emotes": [
            {
              "type": 30,
              "delay": 0.0,
              "extent": 1.0,
              "msg": "ShadowInvasion@4-4_8",
              "max": 4,
              "min": 4
            }
          ],
          "probability": 1.0,
          "quest": "Check4"
        },
        {
          "category": 32,
          "emotes": [
            {
              "type": 30,
              "delay": 0.0,
              "extent": 1.0,
              "msg": "ShadowInvasion@3-3_12",
              "max": 3,
              "min": 3
            }
          ],
          "probability": 1.0,
          "quest": "Check3"
        },
        {
          "category": 32,
          "emotes": [
            {
              "type": 30,
              "delay": 0.0,
              "extent": 1.0,
              "msg": "ShadowInvasion@4-4_9",
              "max": 4,
              "min": 4
            }
          ],
          "probability": 1.0,
          "quest": "OnCooldown"
        }
      ]
    }
  ],
  "changelog": [
    {
      "created": "2023-07-12T22:10:23.0255178Z",
      "author": "ACE.Adapter",
      "comment": "Weenie exported from ACEmulator world database using ACE.Adapter"
    }
  ],
  "isDone": false
}