{
  "wcid": 45750,
  "weenieType": 10,
  "attributes": {
    "strength": {
      "cp_spent": 0,
      "level_from_cp": 0,
      "init_level": 300
    },
    "endurance": {
      "cp_spent": 0,
      "level_from_cp": 0,
      "init_level": 300
    },
    "coordination": {
      "cp_spent": 0,
      "level_from_cp": 0,
      "init_level": 300
    },
    "quickness": {
      "cp_spent": 0,
      "level_from_cp": 0,
      "init_level": 150
    },
    "focus": {
      "cp_spent": 0,
      "level_from_cp": 0,
      "init_level": 350
    },
    "self": {
      "cp_spent": 0,
      "level_from_cp": 0,
      "init_level": 350
    },
    "health": {
      "cp_spent": 0,
      "level_from_cp": 0,
      "init_level": 2850,
      "current": 3000
    },
    "stamina": {
      "cp_spent": 0,
      "level_from_cp": 0,
      "init_level": 500,
      "current": 800
    },
    "mana": {
      "cp_spent": 0,
      "level_from_cp": 0,
      "init_level": 1000,
      "current": 1350
    }
  },
  "body": {
    "body_part_table": [
      {
        "key": 0,
        "value": {
          "dtype": 4,
          "dval": 400,
          "dvar": 0.75,
          "acache": {
            "base_armor": 200,
            "armor_vs_slash": 200,
            "armor_vs_pierce": 200,
            "armor_vs_bludgeon": 200,
            "armor_vs_cold": 200,
            "armor_vs_fire": 200,
            "armor_vs_acid": 200,
            "armor_vs_electric": 200,
            "armor_vs_nether": 0
          },
          "bh": 1,
          "bpsd": {
            "HLF": 0.5,
            "MLF": 0.20000000298023224,
            "LLF": 0.0,
            "HRF": 0.5,
            "MRF": 0.20000000298023224,
            "LRF": 0.0,
            "HLB": 0.0,
            "MLB": 0.0,
            "LLB": 0.0,
            "HRB": 0.0,
            "MRB": 0.0,
            "LRB": 0.0
          }
        }
      },
      {
        "key": 10,
        "value": {
          "dtype": 4,
          "dval": 0,
          "dvar": 0.0,
          "acache": {
            "base_armor": 200,
            "armor_vs_slash": 200,
            "armor_vs_pierce": 200,
            "armor_vs_bludgeon": 200,
            "armor_vs_cold": 200,
            "armor_vs_fire": 200,
            "armor_vs_acid": 200,
            "armor_vs_electric": 200,
            "armor_vs_nether": 0
          },
          "bh": 2,
          "bpsd": {
            "HLF": 0.20000000298023224,
            "MLF": 0.4000000059604645,
            "LLF": 0.5,
            "HRF": 0.20000000298023224,
            "MRF": 0.4000000059604645,
            "LRF": 0.5,
            "HLB": 0.0,
            "MLB": 0.0,
            "LLB": 0.0,
            "HRB": 0.0,
            "MRB": 0.0,
            "LRB": 0.0
          }
        }
      },
      {
        "key": 12,
        "value": {
          "dtype": 4,
          "dval": 400,
          "dvar": 0.75,
          "acache": {
            "base_armor": 200,
            "armor_vs_slash": 200,
            "armor_vs_pierce": 200,
            "armor_vs_bludgeon": 200,
            "armor_vs_cold": 200,
            "armor_vs_fire": 200,
            "armor_vs_acid": 200,
            "armor_vs_electric": 200,
            "armor_vs_nether": 0
          },
          "bh": 3,
          "bpsd": {
            "HLF": 0.0,
            "MLF": 0.0,
            "LLF": 0.25,
            "HRF": 0.0,
            "MRF": 0.0,
            "LRF": 0.25,
            "HLB": 0.0,
            "MLB": 0.0,
            "LLB": 0.0,
            "HRB": 0.0,
            "MRB": 0.0,
            "LRB": 0.0
          }
        }
      },
      {
        "key": 13,
        "value": {
          "dtype": 4,
          "dval": 0,
          "dvar": 0.0,
          "acache": {
            "base_armor": 200,
            "armor_vs_slash": 200,
            "armor_vs_pierce": 200,
            "armor_vs_bludgeon": 200,
            "armor_vs_cold": 200,
            "armor_vs_fire": 200,
            "armor_vs_acid": 200,
            "armor_vs_electric": 200,
            "armor_vs_nether": 0
          },
          "bh": 2,
          "bpsd": {
            "HLF": 0.0,
            "MLF": 0.0,
            "LLF": 0.0,
            "HRF": 0.0,
            "MRF": 0.0,
            "LRF": 0.0,
            "HLB": 0.30000001192092896,
            "MLB": 0.4000000059604645,
            "LLB": 0.5,
            "HRB": 0.30000001192092896,
            "MRB": 0.4000000059604645,
            "LRB": 0.5
          }
        }
      },
      {
        "key": 15,
        "value": {
          "dtype": 4,
          "dval": 400,
          "dvar": 0.75,
          "acache": {
            "base_armor": 200,
            "armor_vs_slash": 200,
            "armor_vs_pierce": 200,
            "armor_vs_bludgeon": 200,
            "armor_vs_cold": 200,
            "armor_vs_fire": 200,
            "armor_vs_acid": 200,
            "armor_vs_electric": 200,
            "armor_vs_nether": 0
          },
          "bh": 3,
          "bpsd": {
            "HLF": 0.0,
            "MLF": 0.0,
            "LLF": 0.0,
            "HRF": 0.0,
            "MRF": 0.0,
            "LRF": 0.0,
            "HLB": 0.0,
            "MLB": 0.0,
            "LLB": 0.25,
            "HRB": 0.0,
            "MRB": 0.0,
            "LRB": 0.25
          }
        }
      },
      {
        "key": 16,
        "value": {
          "dtype": 4,
          "dval": 0,
          "dvar": 0.0,
          "acache": {
            "base_armor": 200,
            "armor_vs_slash": 200,
            "armor_vs_pierce": 200,
            "armor_vs_bludgeon": 200,
            "armor_vs_cold": 200,
            "armor_vs_fire": 200,
            "armor_vs_acid": 200,
            "armor_vs_electric": 200,
            "armor_vs_nether": 0
          },
          "bh": 2,
          "bpsd": {
            "HLF": 0.30000001192092896,
            "MLF": 0.4000000059604645,
            "LLF": 0.25,
            "HRF": 0.30000001192092896,
            "MRF": 0.4000000059604645,
            "LRF": 0.25,
            "HLB": 0.6000000238418579,
            "MLB": 0.5,
            "LLB": 0.25,
            "HRB": 0.6000000238418579,
            "MRB": 0.5,
            "LRB": 0.25
          }
        }
      },
      {
        "key": 17,
        "value": {
          "dtype": 4,
          "dval": 400,
          "dvar": 0.75,
          "acache": {
            "base_armor": 200,
            "armor_vs_slash": 200,
            "armor_vs_pierce": 200,
            "armor_vs_bludgeon": 200,
            "armor_vs_cold": 200,
            "armor_vs_fire": 200,
            "armor_vs_acid": 200,
            "armor_vs_electric": 200,
            "armor_vs_nether": 0
          },
          "bh": 2,
          "bpsd": {
            "HLF": 0.0,
            "MLF": 0.0,
            "LLF": 0.0,
            "HRF": 0.0,
            "MRF": 0.0,
            "LRF": 0.0,
            "HLB": 0.10000000149011612,
            "MLB": 0.10000000149011612,
            "LLB": 0.0,
            "HRB": 0.10000000149011612,
            "MRB": 0.10000000149011612,
            "LRB": 0.0
          }
        }
      }
    ]
  },
  "boolStats": [
    {
      "key": 1,
      "value": 1
    },
    {
      "key": 42,
      "value": 1
    }
  ],
  "intStats": [
    {
      "key": 1,
      "value": 16
    },
    {
      "key": 2,
      "value": 47
    },
    {
      "key": 3,
      "value": 8
    },
    {
      "key": 6,
      "value": -1
    },
    {
      "key": 7,
      "value": -1
    },
    {
      "key": 16,
      "value": 1
    },
    {
      "key": 25,
      "value": 200
    },
    {
      "key": 68,
      "value": 5
    },
    {
      "key": 81,
      "value": 2
    },
    {
      "key": 82,
      "value": 2
    },
    {
      "key": 93,
      "value": 3080
    },
    {
      "key": 133,
      "value": 4
    },
    {
      "key": 146,
      "value": 1100000
    }
  ],
  "didStats": [
    {
      "key": 1,
      "value": 33556732
    },
    {
      "key": 2,
      "value": 150995095
    },
    {
      "key": 3,
      "value": 536871001
    },
    {
      "key": 4,
      "value": 805306407
    },
    {
      "key": 6,
      "value": 67111919
    },
    {
      "key": 7,
      "value": 268435859
    },
    {
      "key": 8,
      "value": 100670283
    },
    {
      "key": 22,
      "value": 872415347
    }
  ],
  "iidStats": [],
  "floatStats": [
    {
      "key": 1,
      "value": 5.0
    },
    {
      "key": 2,
      "value": 0.0
    },
    {
      "key": 3,
      "value": 8.0
    },
    {
      "key": 4,
      "value": 5.0
    },
    {
      "key": 5,
      "value": 2.0
    },
    {
      "key": 12,
      "value": 0.0
    },
    {
      "key": 13,
      "value": 1.0
    },
    {
      "key": 14,
      "value": 1.0
    },
    {
      "key": 15,
      "value": 1.0
    },
    {
      "key": 16,
      "value": 1.0
    },
    {
      "key": 17,
      "value": 1.0
    },
    {
      "key": 18,
      "value": 1.0
    },
    {
      "key": 19,
      "value": 1.0
    },
    {
      "key": 31,
      "value": 12.0
    },
    {
      "key": 36,
      "value": 1.0
    },
    {
      "key": 39,
      "value": 1.5
    },
    {
      "key": 41,
      "value": 180.0
    },
    {
      "key": 64,
      "value": 1.0
    },
    {
      "key": 65,
      "value": 1.0
    },
    {
      "key": 66,
      "value": 1.0
    },
    {
      "key": 67,
      "value": 1.0
    },
    {
      "key": 68,
      "value": 1.0
    },
    {
      "key": 69,
      "value": 1.0
    },
    {
      "key": 70,
      "value": 1.0
    },
    {
      "key": 80,
      "value": 2.0
    },
    {
      "key": 104,
      "value": 10.0
    },
    {
      "key": 122,
      "value": 2.0
    },
    {
      "key": 125,
      "value": 0.0
    }
  ],
  "int64Stats": [],
  "stringStats": [
    {
      "key": 1,
      "value": "Acid Crystal"
    }
  ],
  "skills": [
    {
      "key": 6,
      "value": {
        "level_from_pp": 0,
        "last_used_time": 0.0,
        "init_level": 132,
        "pp": 0,
        "resistance_of_last_check": 0,
        "sac": 2
      }
    },
    {
      "key": 7,
      "value": {
        "level_from_pp": 0,
        "last_used_time": 0.0,
        "init_level": 149,
        "pp": 0,
        "resistance_of_last_check": 0,
        "sac": 2
      }
    },
    {
      "key": 15,
      "value": {
        "level_from_pp": 0,
        "last_used_time": 0.0,
        "init_level": 170,
        "pp": 0,
        "resistance_of_last_check": 0,
        "sac": 2
      }
    },
    {
      "key": 16,
      "value": {
        "level_from_pp": 0,
        "last_used_time": 0.0,
        "init_level": 149,
        "pp": 0,
        "resistance_of_last_check": 0,
        "sac": 2
      }
    },
    {
      "key": 31,
      "value": {
        "level_from_pp": 0,
        "last_used_time": 0.0,
        "init_level": 149,
        "pp": 0,
        "resistance_of_last_check": 0,
        "sac": 2
      }
    },
    {
      "key": 33,
      "value": {
        "level_from_pp": 0,
        "last_used_time": 0.0,
        "init_level": 149,
        "pp": 0,
        "resistance_of_last_check": 0,
        "sac": 2
      }
    },
    {
      "key": 34,
      "value": {
        "level_from_pp": 0,
        "last_used_time": 0.0,
        "init_level": 149,
        "pp": 0,
        "resistance_of_last_check": 0,
        "sac": 2
      }
    },
    {
      "key": 41,
      "value": {
        "level_from_pp": 0,
        "last_used_time": 0.0,
        "init_level": 132,
        "pp": 0,
        "resistance_of_last_check": 0,
        "sac": 2
      }
    },
    {
      "key": 43,
      "value": {
        "level_from_pp": 0,
        "last_used_time": 0.0,
        "init_level": 149,
        "pp": 0,
        "resistance_of_last_check": 0,
        "sac": 2
      }
    },
    {
      "key": 44,
      "value": {
        "level_from_pp": 0,
        "last_used_time": 0.0,
        "init_level": 132,
        "pp": 0,
        "resistance_of_last_check": 0,
        "sac": 2
      }
    },
    {
      "key": 45,
      "value": {
        "level_from_pp": 0,
        "last_used_time": 0.0,
        "init_level": 132,
        "pp": 0,
        "resistance_of_last_check": 0,
        "sac": 2
      }
    },
    {
      "key": 46,
      "value": {
        "level_from_pp": 0,
        "last_used_time": 0.0,
        "init_level": 132,
        "pp": 0,
        "resistance_of_last_check": 0,
        "sac": 2
      }
    }
  ],
  "emoteTable": [
    {
      "key": 3,
      "value": [
        {
          "category": 3,
          "emotes": [
            {
              "type": 88,
              "delay": 0.0,
              "extent": 1.0,
              "msg": "TwistedRefugeKillCount"
            }
          ],
          "probability": 1.0
        }
      ]
    }
  ],
  "generatorTable": [
    {
      "delay": 60.0,
      "frame": {
        "origin": {
          "x": 0.0,
          "y": 0.0,
          "z": 0.0
        },
        "angles": {
          "w": 1.0,
          "x": 0.0,
          "y": 0.0,
          "z": 0.0
        }
      },
      "initCreate": 2,
      "maxNum": 2,
      "objcell_id": 0,
      "probability": -1.0,
      "ptid": 0,
      "shade": 0.0,
      "slot": 0,
      "stackSize": 0,
      "type": 45700,
      "whenCreate": 2,
      "whereCreate": 2
    }
  ],
  "changelog": [
    {
      "created": "2023-07-12T22:10:47.452073Z",
      "author": "ACE.Adapter",
      "comment": "Weenie exported from ACEmulator world database using ACE.Adapter"
    }
  ],
  "isDone": false
}