{
  "wcid": 5859,
  "weenieType": 1,
  "boolStats": [
    {
      "key": 1,
      "value": 1
    },
    {
      "key": 11,
      "value": 1
    },
    {
      "key": 18,
      "value": 1
    },
    {
      "key": 74,
      "value": 1
    }
  ],
  "intStats": [
    {
      "key": 81,
      "value": 1
    },
    {
      "key": 82,
      "value": 1
    },
    {
      "key": 93,
      "value": 1044
    },
    {
      "key": 145,
      "value": 2
    }
  ],
  "didStats": [
    {
      "key": 1,
      "value": 33555051
    },
    {
      "key": 8,
      "value": 100667494
    }
  ],
  "iidStats": [],
  "floatStats": [
    {
      "key": 41,
      "value": 60.0
    },
    {
      "key": 43,
      "value": 5.0
    }
  ],
  "int64Stats": [],
  "stringStats": [
    {
      "key": 1,
      "value": "Unhappy Snowman Generator"
    }
  ],
  "generatorTable": [
    {
      "delay": 1800.0,
      "frame": {
        "origin": {
          "x": 4.0,
          "y": 2.5,
          "z": 0.0
        },
        "angles": {
          "w": 0.707107,
          "x": 0.0,
          "y": 0.0,
          "z": -0.707107
        }
      },
      "initCreate": 1,
      "maxNum": 1,
      "objcell_id": 0,
      "probability": 0.800000011920929,
      "ptid": 0,
      "shade": 0.0,
      "slot": 0,
      "stackSize": -1,
      "type": 5766,
      "whenCreate": 1,
      "whereCreate": 4
    },
    {
      "delay": 1800.0,
      "frame": {
        "origin": {
          "x": 4.0,
          "y": 2.5,
          "z": 0.0
        },
        "angles": {
          "w": 0.707107,
          "x": 0.0,
          "y": 0.0,
          "z": -0.707107
        }
      },
      "initCreate": 1,
      "maxNum": 1,
      "objcell_id": 0,
      "probability": 0.8999999761581421,
      "ptid": 0,
      "shade": 0.0,
      "slot": 1,
      "stackSize": -1,
      "type": 14466,
      "whenCreate": 1,
      "whereCreate": 4
    },
    {
      "delay": 1800.0,
      "frame": {
        "origin": {
          "x": -8.0,
          "y": -5.5,
          "z": 0.0
        },
        "angles": {
          "w": 0.707107,
          "x": 0.0,
          "y": 0.0,
          "z": -0.707107
        }
      },
      "initCreate": 1,
      "maxNum": 1,
      "objcell_id": 0,
      "probability": 1.0,
      "ptid": 0,
      "shade": 0.0,
      "slot": 2,
      "stackSize": -1,
      "type": 9009,
      "whenCreate": 1,
      "whereCreate": 4
    }
  ],
  "changelog": [
    {
      "created": "2023-07-12T21:59:16.9778538Z",
      "author": "ACE.Adapter",
      "comment": "Weenie exported from ACEmulator world database using ACE.Adapter"
    }
  ],
  "isDone": false
}