{
  "wcid": 8135,
  "weenieType": 8,
  "pageDataList": {
    "maxNumCharsPerPage": 1000,
    "maxNumPages": 1,
    "pages": [
      {
        "authorAccount": "prewritten",
        "authorID": 4294967295,
        "authorName": "Zarea bint Zia",
        "ignoreAuthor": 0,
        "pageText": "\nTo my esteemed colleagues, Aliester the Loquacious and Gondo Kanezo:\n\n\nGentlemen, I sense great events are afoot in our land. The ley lines have become unstable, strange energies are accumulating at menhir rings, and several new rock formations have sprung up in the Linvak range, in the north mountains near Mt. Esper, and in the Obsidian Plains. Keep your scouts alert for more geomantic activity.\n"
      }
    ]
  },
  "boolStats": [
    {
      "key": 22,
      "value": 0
    }
  ],
  "intStats": [
    {
      "key": 1,
      "value": 8192
    },
    {
      "key": 5,
      "value": 25
    },
    {
      "key": 8,
      "value": 5
    },
    {
      "key": 9,
      "value": 0
    },
    {
      "key": 16,
      "value": 8
    },
    {
      "key": 19,
      "value": 5
    },
    {
      "key": 93,
      "value": 1044
    },
    {
      "key": 114,
      "value": 1
    }
  ],
  "didStats": [
    {
      "key": 1,
      "value": 33554773
    },
    {
      "key": 3,
      "value": 536870932
    },
    {
      "key": 8,
      "value": 100668176
    },
    {
      "key": 22,
      "value": 872415275
    }
  ],
  "iidStats": [],
  "floatStats": [
    {
      "key": 54,
      "value": 1.0
    }
  ],
  "int64Stats": [],
  "stringStats": [
    {
      "key": 1,
      "value": "Zarea's Notes on Geomancy"
    },
    {
      "key": 15,
      "value": "A letter from Zarea bint Zia."
    },
    {
      "key": 16,
      "value": "A letter from Zarea bint Zia to her fellow sages."
    }
  ],
  "changelog": [
    {
      "created": "2023-07-12T22:00:03.3291822Z",
      "author": "ACE.Adapter",
      "comment": "Weenie exported from ACEmulator world database using ACE.Adapter"
    }
  ],
  "isDone": false
}