{
  "wcid": 9066,
  "weenieType": 44,
  "boolStats": [
    {
      "key": 22,
      "value": 1
    },
    {
      "key": 23,
      "value": 1
    }
  ],
  "intStats": [
    {
      "key": 1,
      "value": 128
    },
    {
      "key": 5,
      "value": 70
    },
    {
      "key": 8,
      "value": 20
    },
    {
      "key": 9,
      "value": 0
    },
    {
      "key": 11,
      "value": 1
    },
    {
      "key": 12,
      "value": 1
    },
    {
      "key": 13,
      "value": 70
    },
    {
      "key": 14,
      "value": 20
    },
    {
      "key": 15,
      "value": 100
    },
    {
      "key": 16,
      "value": 524296
    },
    {
      "key": 19,
      "value": 100
    },
    {
      "key": 93,
      "value": 1044
    },
    {
      "key": 94,
      "value": 8192
    },
    {
      "key": 150,
      "value": 103
    },
    {
      "key": 151,
      "value": 11
    }
  ],
  "didStats": [
    {
      "key": 1,
      "value": 33556961
    },
    {
      "key": 3,
      "value": 536870932
    },
    {
      "key": 8,
      "value": 100671337
    },
    {
      "key": 22,
      "value": 872415275
    }
  ],
  "iidStats": [],
  "floatStats": [],
  "int64Stats": [],
  "stringStats": [
    {
      "key": 1,
      "value": "Puzzle Box"
    },
    {
      "key": 14,
      "value": "You have no idea how to use this item."
    },
    {
      "key": 15,
      "value": "A strange old puzzle box."
    },
    {
      "key": 16,
      "value": "A strange old puzzle box. There are two slots, each about the size of a small book, on opposing sides. There is a symbol inscribed on its metal surface; an eight-pointed starburst shape overlaid on a swirling portal. In the heart of the starburst is a crashing wave. Within the folds of the portal swirl are four glass beads, red, blue, violet, and green."
    }
  ],
  "changelog": [
    {
      "created": "2023-07-12T22:00:23.0402586Z",
      "author": "ACE.Adapter",
      "comment": "Weenie exported from ACEmulator world database using ACE.Adapter"
    }
  ],
  "isDone": false
}