{
  "wcid": 9081,
  "weenieType": 8,
  "pageDataList": {
    "maxNumCharsPerPage": 1000,
    "maxNumPages": 1,
    "pages": [
      {
        "authorAccount": "prewritten",
        "authorID": 4294967295,
        "authorName": "Unknown",
        "ignoreAuthor": 0,
        "pageText": "\n\n[ You cannot read this text, and must get it translated. ]\n"
      }
    ]
  },
  "boolStats": [
    {
      "key": 22,
      "value": 0
    },
    {
      "key": 23,
      "value": 1
    },
    {
      "key": 69,
      "value": 0
    }
  ],
  "intStats": [
    {
      "key": 1,
      "value": 8192
    },
    {
      "key": 5,
      "value": 50
    },
    {
      "key": 8,
      "value": 50
    },
    {
      "key": 9,
      "value": 0
    },
    {
      "key": 16,
      "value": 8
    },
    {
      "key": 19,
      "value": 10
    },
    {
      "key": 93,
      "value": 1044
    }
  ],
  "didStats": [
    {
      "key": 1,
      "value": 33554771
    },
    {
      "key": 3,
      "value": 536870932
    },
    {
      "key": 8,
      "value": 100668117
    },
    {
      "key": 22,
      "value": 872415275
    }
  ],
  "iidStats": [],
  "floatStats": [
    {
      "key": 39,
      "value": 1.22
    },
    {
      "key": 54,
      "value": 0.3
    }
  ],
  "int64Stats": [],
  "stringStats": [
    {
      "key": 1,
      "value": "Decoded Untranslated Text"
    },
    {
      "key": 15,
      "value": "A book, printed in clean yet ornate script."
    },
    {
      "key": 16,
      "value": "A book, printed in clean yet ornate Yalaini script. You cannot read it."
    }
  ],
  "changelog": [
    {
      "created": "2023-07-12T22:00:23.3389452Z",
      "author": "ACE.Adapter",
      "comment": "Weenie exported from ACEmulator world database using ACE.Adapter"
    }
  ],
  "isDone": false
}